fabric_auditor/__init__.py
fabric_auditor/core.py
fabric_auditor-0.1.2.1.dist-info/licenses/LICENSE
fabric_auditor-0.1.2.1.dist-info/METADATA
fabric_auditor-0.1.2.1.dist-info/WHEEL
fabric_auditor-0.1.2.1.dist-info/top_level.txt
fabric_auditor-0.1.2.1.dist-info/RECORD
