Metadata-Version: 2.4
Name: fabric_auditor
Version: 0.1.2.1
Summary: Uma biblioteca para auditar e resumir Notebooks do Microsoft Fabric usando LLMs com uma visão de Engenharia de Dados.
Author-email: Flavio Bezerra <flavio.bezerra@example.com>
License: MIT License
Project-URL: Homepage, https://github.com/flavio-bezerra/fabric-auditor
Project-URL: Bug Tracker, https://github.com/flavio-bezerra/fabric-auditor/issues
Keywords: microsoft fabric,auditor,llm,notebooks,azure
Classifier: Programming Language :: Python :: 3
Classifier: License :: OSI Approved :: MIT License
Classifier: Operating System :: OS Independent
Requires-Python: >=3.9
License-File: LICENSE
Requires-Dist: requests
Requires-Dist: openai==1.51.0
Requires-Dist: pydantic==2.12.2
Requires-Dist: httpx==0.27.2
Requires-Dist: azure-identity
Requires-Dist: azure-keyvault-secrets
Dynamic: license-file
